<?xml version="1.0" encoding="UTF-8" ?><!DOCTYPE generatorConfiguration PUBLIC "-//mybatis.org//DTD MyBatis Generator Configuration 1.0//EN" "http://mybatis.org/dtd/mybatis-generator-config_1_0.dtd" ><generatorConfiguration >  <context id="vesmile_la_context" >    <commentGenerator>    	<property name="suppressAllComments" value="true" />     </commentGenerator>        <jdbcConnection driverClass="com.mysql.jdbc.Driver" connectionURL="jdbc:mysql://127.0.0.1:3306/demodb" userId="demo" password="ab1234cD" />        <javaTypeResolver>    	<property name="forceBigDecimals" value="false"/>    </javaTypeResolver>        <javaModelGenerator targetPackage="com.vesmile.webappla.model" targetProject="vsf" >    	<property name="enableSubPackages" value="true" />        	<property name="trimStrings" value="true" />    </javaModelGenerator>        <sqlMapGenerator targetPackage="sqlMaps" targetProject="vsf/src/resource" >        <property name="enableSubPackages" value="false" />     </sqlMapGenerator>        <javaClientGenerator targetPackage="com.vesmile.webappla.dao.mybatis.client" targetProject="vsf" type="XMLMAPPER" />    <table schema="demodb" tableName="LA_Home" domainObjectName="Home">    	<columnRenamingRule searchString="^lah_"/>    </table>    <table schema="demodb" tableName="LA_Home_Param" domainObjectName="HomeParam">    	<columnRenamingRule searchString="^lahp_"/>    </table>    <table schema="demodb" tableName="LA_Log" domainObjectName="Log">    	<columnRenamingRule searchString="^lal_"/>    </table>    <table schema="demodb" tableName="LA_Menu" domainObjectName="Menu">    	<columnRenamingRule searchString="^lam_"/>    </table>    <table schema="demodb" tableName="LA_Order" domainObjectName="Order">    	<columnRenamingRule searchString="^lao_"/>    </table>    <table schema="demodb" tableName="LA_Property" domainObjectName="Property">    	<columnRenamingRule searchString="^lap_"/>    </table>    <table schema="demodb" tableName="LA_Property_Param" domainObjectName="PropertyParam">    	<columnRenamingRule searchString="^lapp_"/>    </table>    <table schema="demodb" tableName="LA_Sys_Param" domainObjectName="SysParam">    	<columnRenamingRule searchString="^lasp_"/>    </table>    <table schema="demodb" tableName="LA_User" domainObjectName="User">    	<columnRenamingRule searchString="^lau_"/>    </table>    <table schema="demodb" tableName="LA_User_Priv" domainObjectName="UserPriv">    	<columnRenamingRule searchString="^laup_"/>    </table>    <table schema="demodb" tableName="LA_User_Right" domainObjectName="UserRight">    	<columnRenamingRule searchString="^laur_"/>    </table>    <table schema="demodb" tableName="LA_View_History" domainObjectName="ViewHistory">    	<columnRenamingRule searchString="^lavh_"/>    </table>  </context></generatorConfiguration>